__init__.py
main.py
models.py
utils.py
github_review_requested-0.2.1.dist-info/METADATA
github_review_requested-0.2.1.dist-info/WHEEL
github_review_requested-0.2.1.dist-info/entry_points.txt
github_review_requested-0.2.1.dist-info/top_level.txt
github_review_requested-0.2.1.dist-info/RECORD
