Metadata-Version: 2.1
Name: github-review-requested
Version: 0.2.1
Summary: A CLI tool to view github review requested
Home-page: https://github.com/mathieumontgomery/github-review-requested
Author: Mathieu Montgomery
Author-email: mathieu.montgomery@mailbox.org
Classifier: Programming Language :: Python :: 3
Classifier: License :: OSI Approved :: MIT License
Classifier: Operating System :: OS Independent
Requires-Python: >=3.8
Requires-Dist: certifi (>=2024.6.2)
Requires-Dist: charset-normalizer (>=3.3.2)
Requires-Dist: click (>=8.1.7)
Requires-Dist: humanize (>=4.9.0)
Requires-Dist: idna (>=3.7)
Requires-Dist: requests (>=2.32.3)
Requires-Dist: rich (>=13.5.3)
Requires-Dist: urllib3 (>=2.2.1)
Requires-Dist: wcwidth (>=0.2.13)
